decore/__init__.py
decore/_version.py
decore/decore.py
decore/version.info
decore-0.0.4.dist-info/licenses/LICENSE
decore-0.0.4.dist-info/METADATA
decore-0.0.4.dist-info/WHEEL
decore-0.0.4.dist-info/top_level.txt
decore-0.0.4.dist-info/RECORD
